request_response_json_serializer
