Metadata-Version: 1.0
Name: request-response-json-serializer
Version: 0.0.2
Summary: Python框架Django，Flask序列化request和response
Home-page: https://github.com/RunningFaster/request-response-serializer.git
Author: RunningFaster
Author-email: ren754203791@126.com
License: License
Platform: UNKNOWN
